karrio/server/manager/__init__.py
karrio/server/manager/admin.py
karrio/server/manager/apps.py
karrio/server/manager/models.py
karrio/server/manager/router.py
karrio/server/manager/signals.py
karrio/server/manager/urls.py
karrio/server/manager/migrations/0001_initial.py
karrio/server/manager/migrations/0002_auto_20201127_0721.py
karrio/server/manager/migrations/0003_auto_20201230_0820.py
karrio/server/manager/migrations/0004_auto_20210125_2125.py
karrio/server/manager/migrations/0005_auto_20210216_0758.py
karrio/server/manager/migrations/0006_auto_20210307_0438.py
karrio/server/manager/migrations/0006_auto_20210308_0302.py
karrio/server/manager/migrations/0007_merge_20210311_1428.py
karrio/server/manager/migrations/0008_remove_shipment_doc_images.py
karrio/server/manager/migrations/0009_auto_20210326_1425.py
karrio/server/manager/migrations/0010_auto_20210403_1404.py
karrio/server/manager/migrations/0011_auto_20210426_1924.py
karrio/server/manager/migrations/0012_auto_20210427_1319.py
karrio/server/manager/migrations/0013_customs_invoice_date.py
karrio/server/manager/migrations/0014_auto_20210515_0928.py
karrio/server/manager/migrations/0015_auto_20210601_0340.py
karrio/server/manager/migrations/0016_shipment_archived.py
karrio/server/manager/migrations/0017_auto_20210629_1650.py
karrio/server/manager/migrations/0018_auto_20210705_1049.py
karrio/server/manager/migrations/0019_auto_20210722_1131.py
karrio/server/manager/migrations/0020_tracking_messages.py
karrio/server/manager/migrations/0021_tracking_estimated_delivery.py
karrio/server/manager/migrations/0022_auto_20211122_2100.py
karrio/server/manager/migrations/0023_auto_20211227_2141.py
karrio/server/manager/migrations/0024_alter_parcel_items.py
karrio/server/manager/migrations/0025_auto_20220113_1158.py
karrio/server/manager/migrations/0026_parcel_reference_number.py
karrio/server/manager/migrations/0027_custom_migration_2021_1.py
karrio/server/manager/migrations/0028_auto_20220303_1153.py
karrio_server_manager-2026.1.4.dist-info/METADATA
karrio_server_manager-2026.1.4.dist-info/WHEEL
karrio_server_manager-2026.1.4.dist-info/top_level.txt
karrio_server_manager-2026.1.4.dist-info/RECORD
